TextLoader.py
TextLoader-0.0.9.dist-info/LICENSE
TextLoader-0.0.9.dist-info/METADATA
TextLoader-0.0.9.dist-info/WHEEL
TextLoader-0.0.9.dist-info/top_level.txt
TextLoader-0.0.9.dist-info/RECORD
