Metadata-Version: 2.1
Name: TextLoader
Version: 0.0.9
Summary: Load text in any encoding and convert each line to a list
Home-page: https://github.com/so686so/TextLoader
Author: SoByungJun
Author-email: so686so@gmail.com
Classifier: Programming Language :: Python :: 3
Classifier: License :: OSI Approved :: MIT License
Classifier: Operating System :: OS Independent
Requires-Python: >=3.8
License-File: LICENSE
Requires-Dist: chardet
